{
  "id": "2f0ea814-9b76-47e9-a49e-a0cccbc94430",
  "prevId": "09a616c9-8843-4c80-9504-49413a98c469",
  "version": "7",
  "dialect": "postgresql",
  "tables": {
    "public.bosses": {
      "name": "bosses",
      "schema": "",
      "columns": {
        "id": {
          "name": "id",
          "type": "text",
          "primaryKey": true,
          "notNull": true
        },
        "hp": {
          "name": "hp",
          "type": "bigint",
          "primaryKey": false,
          "notNull": true
        },
        "current_hp": {
          "name": "current_hp",
          "type": "bigint",
          "primaryKey": false,
          "notNull": true
        }
      },
      "indexes": {
        "bosses_current_hp_idx": {
          "name": "bosses_current_hp_idx",
          "columns": [
            {
              "expression": "current_hp",
              "isExpression": false,
              "asc": true,
              "nulls": "last"
            }
          ],
          "isUnique": false,
          "with": {},
          "method": "btree",
          "where": "current_hp > 0",
          "concurrently": false
        }
      },
      "foreignKeys": {},
      "compositePrimaryKeys": {},
      "uniqueConstraints": {},
      "policies": {},
      "checkConstraints": {},
      "isRLSEnabled": false
    },
    "public.consumer_offset": {
      "name": "consumer_offset",
      "schema": "",
      "columns": {
        "id": {
          "name": "id",
          "type": "text",
          "primaryKey": true,
          "notNull": true
        },
        "last_event_sequence": {
          "name": "last_event_sequence",
          "type": "text",
          "primaryKey": false,
          "notNull": true
        }
      },
      "indexes": {},
      "foreignKeys": {},
      "compositePrimaryKeys": {},
      "uniqueConstraints": {},
      "policies": {},
      "checkConstraints": {},
      "isRLSEnabled": false
    },
    "public.contributions": {
      "name": "contributions",
      "schema": "",
      "columns": {
        "player_id": {
          "name": "player_id",
          "type": "text",
          "primaryKey": false,
          "notNull": true
        },
        "boss_id": {
          "name": "boss_id",
          "type": "text",
          "primaryKey": false,
          "notNull": true
        },
        "damage": {
          "name": "damage",
          "type": "bigint",
          "primaryKey": false,
          "notNull": true
        }
      },
      "indexes": {
        "boss_id_damage_idx": {
          "name": "boss_id_damage_idx",
          "columns": [
            {
              "expression": "boss_id",
              "isExpression": false,
              "asc": true,
              "nulls": "last"
            },
            {
              "expression": "damage",
              "isExpression": false,
              "asc": false,
              "nulls": "last"
            }
          ],
          "isUnique": false,
          "with": {},
          "method": "btree",
          "concurrently": false
        }
      },
      "foreignKeys": {
        "contributions_boss_id_bosses_id_fk": {
          "name": "contributions_boss_id_bosses_id_fk",
          "tableFrom": "contributions",
          "columnsFrom": [
            "boss_id"
          ],
          "tableTo": "bosses",
          "columnsTo": [
            "id"
          ],
          "onUpdate": "no action",
          "onDelete": "no action"
        }
      },
      "compositePrimaryKeys": {
        "contributions_pk": {
          "name": "contributions_pk",
          "columns": [
            "player_id",
            "boss_id"
          ]
        }
      },
      "uniqueConstraints": {},
      "policies": {},
      "checkConstraints": {},
      "isRLSEnabled": false
    },
    "public.reward_claims": {
      "name": "reward_claims",
      "schema": "",
      "columns": {
        "player_id": {
          "name": "player_id",
          "type": "text",
          "primaryKey": false,
          "notNull": true
        },
        "boss_id": {
          "name": "boss_id",
          "type": "text",
          "primaryKey": false,
          "notNull": true
        },
        "timestamp": {
          "name": "timestamp",
          "type": "bigint",
          "primaryKey": false,
          "notNull": true
        }
      },
      "indexes": {
        "reward_claims_player_id_idx": {
          "name": "reward_claims_player_id_idx",
          "columns": [
            {
              "expression": "player_id",
              "isExpression": false,
              "asc": true,
              "nulls": "last"
            }
          ],
          "isUnique": false,
          "with": {},
          "method": "btree",
          "concurrently": false
        },
        "reward_claims_boss_id_idx": {
          "name": "reward_claims_boss_id_idx",
          "columns": [
            {
              "expression": "boss_id",
              "isExpression": false,
              "asc": true,
              "nulls": "last"
            }
          ],
          "isUnique": false,
          "with": {},
          "method": "btree",
          "concurrently": false
        }
      },
      "foreignKeys": {
        "reward_claims_boss_id_bosses_id_fk": {
          "name": "reward_claims_boss_id_bosses_id_fk",
          "tableFrom": "reward_claims",
          "columnsFrom": [
            "boss_id"
          ],
          "tableTo": "bosses",
          "columnsTo": [
            "id"
          ],
          "onUpdate": "no action",
          "onDelete": "no action"
        }
      },
      "compositePrimaryKeys": {
        "reward_claims_pk": {
          "name": "reward_claims_pk",
          "columns": [
            "player_id",
            "boss_id"
          ]
        }
      },
      "uniqueConstraints": {},
      "policies": {},
      "checkConstraints": {},
      "isRLSEnabled": false
    }
  },
  "enums": {},
  "schemas": {},
  "views": {},
  "sequences": {},
  "roles": {},
  "policies": {},
  "_meta": {
    "columns": {},
    "schemas": {},
    "tables": {}
  }
}